rpa_shopee/__init__.py
rpa_shopee/api/AdvertisementBillApi.py
rpa_shopee/api/BillApi.py
rpa_shopee/api/ShopApi.py
rpa_shopee/api/__init__.py
rpa_shopee/command/__init__.py
rpa_shopee/command/ads/AdsService.py
rpa_shopee/command/ads/__init__.py
rpa_shopee/command/bill/BillService.py
rpa_shopee/command/bill/__init__.py
rpa_shopee/request/BillRequest.py
rpa_shopee/request/__init__.py
rpa_shopee/service/ShopeeService.py
rpa_shopee/service/__init__.py
rpa_shopee-1.0.3.dist-info/LICENSE
rpa_shopee-1.0.3.dist-info/METADATA
rpa_shopee-1.0.3.dist-info/WHEEL
rpa_shopee-1.0.3.dist-info/top_level.txt
rpa_shopee-1.0.3.dist-info/RECORD
